createx/__init__.py
createx/__main__.py
createx/deployments.json
createx/main.py
createx/manifest.json
createx/package.py
createx/py.typed
createx-0.1.2.dist-info/licenses/LICENSE
createx-0.1.2.dist-info/METADATA
createx-0.1.2.dist-info/WHEEL
createx-0.1.2.dist-info/entry_points.txt
createx-0.1.2.dist-info/top_level.txt
createx-0.1.2.dist-info/RECORD
