Metadata-Version: 2.4
Name: createx
Version: 0.1.2
Summary: Ape-based Python SDK for CreateX
Author-email: ApeWorX <admin@apeworx.io>
Requires-Python: >=3.11
License-File: LICENSE
Requires-Dist: eth-ape<1,>=0.8
Dynamic: license-file
